bs_admin_utils/__init__.py
bs_admin_utils/api.py
bs_admin_utils/decorators.py
bs_admin_utils/model.py
bs_admin_utils/vercode.py
bs_admin_utils/websocket.py
bs_admin_utils/static/arial.ttf
bs_admin_utils/static/nstc.ttf
bs_admin_utils-1.1.7.dist-info/LICENSE
bs_admin_utils-1.1.7.dist-info/METADATA
bs_admin_utils-1.1.7.dist-info/WHEEL
bs_admin_utils-1.1.7.dist-info/top_level.txt
bs_admin_utils-1.1.7.dist-info/zip-safe
bs_admin_utils-1.1.7.dist-info/RECORD
