Metadata-Version: 2.1
Name: bs-admin-utils
Version: 1.1.7
Summary: Blacksheep admin backend utils classes and function.
Author: kiki-kanri
Author-email: a470666@gmail.com
Classifier: License :: Freely Distributable
Requires-Python: >=3.8
License-File: LICENSE
Requires-Dist: beanie
Requires-Dist: blacksheep
Requires-Dist: kiki-utils
Requires-Dist: pillow
Requires-Dist: uvicorn
